{ "_id" : { "$oid" : "5b96ce7f76d7d136c19110c0" }, "address" : { "street" : { "name" : "R. Angela Mirella", "number" : "354", "complement" : "Térreo", "cep" : "06411-330" }, "state" : { "name" : "São Paulo", "initials" : "SP", "city" : "Barueri" }, "location" : { "type" : "Point", "coordinates" : [ -47.09893532, -23.4966492 ] } }, "name" : "Fundação Pró-Sangue (Barueri)", "telephone" : "0800-55-0300", "__v" : 0 }
{ "_id" : { "$oid" : "5b96cf0376d7d136c19110c1" }, "address" : { "street" : { "name" : "Av. Enéas Carvalho Aguiar", "number" : "155", "complement" : "1º andar", "cep" : "05403-000" }, "state" : { "name" : "São Paulo", "initials" : "SP", "city" : "São Paulo" }, "location" : { "type" : "Point", "coordinates" : [ -46.6688705, -23.5570772 ] } }, "name" : "Fundação Pró-Sangue (São Paulo - Posto Clínicas)", "telephone" : "0800-55-0300", "__v" : 0 }
{ "_id" : { "$oid" : "5b96d2cd93ac9c3832ce713e" }, "address" : { "street" : { "name" : "R. José Bonifácio", "number" : "1641", "complement" : "", "cep" : "09960-120" }, "state" : { "name" : "São Paulo", "initials" : "SP", "city" : "Diadema" }, "location" : { "type" : "Point", "coordinates" : [ -46.6688705, -23.5570772 ] } }, "name" : "Hospital Estadual de Diadema", "description" : "De segunda a sexta-feira, das 7h às 15h (com intervalo para almoço)", "telephone" : "(11) 3583-1400", "__v" : 0 }
